reyncher_mcp_demp/__init__.py
reyncher_mcp_demp-0.1.0.dist-info/METADATA
reyncher_mcp_demp-0.1.0.dist-info/WHEEL
reyncher_mcp_demp-0.1.0.dist-info/entry_points.txt
reyncher_mcp_demp-0.1.0.dist-info/RECORD
