Metadata-Version: 2.4
Name: reyncher-mcp-demp
Version: 0.1.0
Summary: Add your description here
Author-email: reyncherrr <xhw99493133@foxmail.com>
Requires-Python: >=3.13
Requires-Dist: mcp[cli]>=1.11.0
